odoo/addons/mrp_bom_matrix_report/README.rst
odoo/addons/mrp_bom_matrix_report/__init__.py
odoo/addons/mrp_bom_matrix_report/__manifest__.py
odoo/addons/mrp_bom_matrix_report/i18n/fr.po
odoo/addons/mrp_bom_matrix_report/i18n/mrp_bom_matrix_report.pot
odoo/addons/mrp_bom_matrix_report/models/__init__.py
odoo/addons/mrp_bom_matrix_report/models/mrp_bom_matrix_report.py
odoo/addons/mrp_bom_matrix_report/readme/CONTRIBUTORS.rst
odoo/addons/mrp_bom_matrix_report/readme/DESCRIPTION.rst
odoo/addons/mrp_bom_matrix_report/readme/USAGE.rst
odoo/addons/mrp_bom_matrix_report/security/ir.model.access.csv
odoo/addons/mrp_bom_matrix_report/static/description/icon.png
odoo/addons/mrp_bom_matrix_report/static/description/index.html
odoo/addons/mrp_bom_matrix_report/views/mrp_bom_matrix_report_views.xml
odoo12_addon_mrp_bom_matrix_report-12.0.1.0.1.dist-info/METADATA
odoo12_addon_mrp_bom_matrix_report-12.0.1.0.1.dist-info/RECORD
odoo12_addon_mrp_bom_matrix_report-12.0.1.0.1.dist-info/WHEEL
odoo12_addon_mrp_bom_matrix_report-12.0.1.0.1.dist-info/top_level.txt
